[
  {
    "email": "",
    "firstName": "",
    "lastName": "",
    "subject(s)": "[]",
    "video": "",
    "bio": "",
    "level": "",
    "price": "",
    "location": "",
    "experince": "",
    "rating": "",
    "paymentsDetails:": ""
  },
  {
    "email": "",
    "firstName": "",
    "lastName": "",
    "subject(s)": "[]",
    "video": "",
    "bio": "",
    "level": "",
    "price": "",
    "location": "",
    "experince": "",
    "rating": "",
    "paymentsDetails:": ""
  },
  {
    "email": "",
    "firstName": "",
    "lastName": "",
    "subject(s)": "[]",
    "video": "",
    "bio": "",
    "level": "",
    "price": "",
    "location": "",
    "experince": "",
    "rating": "",
    "paymentsDetails:": ""
  },
  {
    "email": "",
    "firstName": "",
    "lastName": "",
    "subject(s)": "[]",
    "video": "",
    "bio": "",
    "level": "",
    "price": "",
    "location": "",
    "experince": "",
    "rating": "",
    "paymentsDetails:": ""
  },
  {
    "email": "",
    "firstName": "",
    "lastName": "",
    "subject(s)": "[]",
    "video": "",
    "bio": "",
    "level": "",
    "price": "",
    "location": "",
    "experince": "",
    "rating": "",
    "paymentsDetails:": ""
  }
]
